discordBotTranslation/__init__.py
discordBotTranslation/disnake.py
discordBotTranslation/exceptions.py
discordBotTranslation/formatting.py
discordBotTranslation/main.py
discordBotTranslation/type.py
discordBot_translation_Philip_Sagan-0.0.2.dist-info/METADATA
discordBot_translation_Philip_Sagan-0.0.2.dist-info/WHEEL
discordBot_translation_Philip_Sagan-0.0.2.dist-info/license.txt
discordBot_translation_Philip_Sagan-0.0.2.dist-info/top_level.txt
discordBot_translation_Philip_Sagan-0.0.2.dist-info/RECORD
