Metadata-Version: 2.1
Name: discordBot-translation-Philip-Sagan
Version: 0.0.2
Summary: Package to translate your discord bots
Home-page: https://github.com/yatochka-dev/discordBot-translation
Author: Philip Sagan
Author-email: philipchef13@gmail.com
Classifier: Programming Language :: Python :: 3
Classifier: License :: OSI Approved :: MIT License
Classifier: Operating System :: OS Independent
License-File: license.txt
Requires-Dist: disnake (>=2.*.*)
